{
  "project_info": {
    "project_number": "486807447068",
    "project_id": "alphanew-f0421",
    "storage_bucket": "alphanew-f0421.appspot.com"
  },
  "client": [
    {
      "client_info": {
        "mobilesdk_app_id": "1:486807447068:android:999edfe72a78fd89a7a1d9",
        "android_client_info": {
          "package_name": "com.flyconcept.alphanew"
        }
      },
      "oauth_client": [
        {
          "client_id": "486807447068-l1na66pk0p0bq562p4inv4fni2hafh2u.apps.googleusercontent.com",
          "client_type": 3
        }
      ],
      "api_key": [
        {
          "current_key": "AIzaSyDDK_qw3ikoNLEbHMt6Jcd742yj9dr3Y0E"
        }
      ],
      "services": {
        "appinvite_service": {
          "other_platform_oauth_client": [
            {
              "client_id": "486807447068-l1na66pk0p0bq562p4inv4fni2hafh2u.apps.googleusercontent.com",
              "client_type": 3
            }
          ]
        }
      }
    }
  ],
  "configuration_version": "1"
}